[
    {
        "phonetics": "pekā I Th",
        "meaning": "'white marble, alabaster, antimony'",
        "origin_explanation": "from Gk. phouka, transcription of Heb. pūk 'black paint'",
        "ethiopic_word": "",
        "amharic_meaning": ""
    },
    {
        "phonetics": "pekā II Th (T)",
        "meaning": "'leg of a chair'",
        "origin_explanation": "the translation is doubtful. Tayyä may have been misled by the occurrence of the word manbar 'chair', in Henoch 18:8.",
        "ethiopic_word": "",
        "amharic_meaning": ""
    },
    {
        "phonetics": "pilās, pilās TAN i TAN, (L) pilāsä TAN, (T.M) pilāso TAN",
        "meaning": "'temple, pavilion, gate, (T.M) tent, (T) place for sacrificing'",
        "origin_explanation": "from Gk. pylēs, gen.sg of pylē 'gate'.",
        "ethiopic_word": "",
        "amharic_meaning": ""
    },
    {
        "phonetics": "pelastos TANMA (D 1408,T)",
        "meaning": "'shield and spear, (M) soldier who carries a spear'",
        "origin_explanation": "from Gk. peltastēs 'carrier of a light shield'.",
        "ethiopic_word": "",
        "amharic_meaning": ""
    },
    {
        "phonetics": "pänä (pl. pänāt) T",
        "meaning": "'lamp, torch'",
        "origin_explanation": "from Gk. phanē 'torch'; also in Tna.Amh. fana.",
        "ethiopic_word": "",
        "amharic_meaning": ""
    },
    {
        "phonetics": "penamu T`o` (T), penamu T`o` (M)",
        "meaning": "'Satan'",
        "origin_explanation": "from Gk. pneuma 'spirit'; also päwnumä, pänəwämä, päwəwmä (Euringer, ZS 7[1929],74; Dobberahn 152).",
        "ethiopic_word": "",
        "amharic_meaning": ""
    },
    {
        "phonetics": "pantayon I T`T`T`T`",
        "meaning": "'sundial'",
        "origin_explanation": "from Gk. plinthion 'sundial'.",
        "ethiopic_word": "",
        "amharic_meaning": ""
    },
    {
        "phonetics": "pantayon II T`T`T`T`",
        "meaning": "'the difference in days between a solar year and a lunar year'",
        "origin_explanation": "is a misreading of t`ntayon T`T`T`T`, for which see below.",
        "ethiopic_word": "",
        "amharic_meaning": ""
    },
    {
        "phonetics": "pāpā TT (MA)",
        "meaning": "see pappās.",
        "origin_explanation": "",
        "ethiopic_word": "",
        "amharic_meaning": ""
    },
    {
        "phonetics": "papirā, paperā, päperā, pepirā T`T`G` i T`T`G` i T`T`G`, (K) papir T`T`G`",
        "meaning": "'purple'",
        "origin_explanation": "from Gk. porphyra 'purple dye'; also Ar. firfir (Rüžička 6). See also papperā, below.",
        "ethiopic_word": "",
        "amharic_meaning": ""
    },
    {
        "phonetics": "papirā lāy, päperā lāy",
        "meaning": "'scarlet'",
        "origin_explanation": "from Gk. porphyra 'purple dye'; also Ar. firfir (Rüžička 6). See also papperā, below.",
        "ethiopic_word": "",
        "amharic_meaning": ""
    },
    {
        "phonetics": "papara (T.M)",
        "meaning": "'dye purple' (denominative)",
        "origin_explanation": "from Gk. porphyra 'purple dye'; also Ar. firfir (Rüžička 6). See also papperā, below.",
        "ethiopic_word": "",
        "amharic_meaning": ""
    },
    {
        "phonetics": "pāpirā T`T`G` (K.D. 684, 1392 'papyrus'); (T)",
        "meaning": "'tar, pitch'",
        "origin_explanation": "from Gk. papyros 'papyrus'",
        "ethiopic_word": "",
        "amharic_meaning": ""
    },
    {
        "phonetics": "papare, papare T`T`G` i T`T`G`",
        "meaning": "'red pepper'",
        "origin_explanation": "from Gk. peperi 'pepper'. See also barbarre, above.",
        "ethiopic_word": "",
        "amharic_meaning": ""
    },
    {
        "phonetics": "perkā T`C`H` (T.M)",
        "meaning": "'chickpea'",
        "origin_explanation": "see also perkā.",
        "ethiopic_word": "",
        "amharic_meaning": ""
    },
    {
        "phonetics": "pərezbitər T`N`N`T`C`",
        "meaning": "'priest'",
        "origin_explanation": "from Gk. presbyteros 'priest'. See also parəzporos.",
        "ethiopic_word": "",
        "amharic_meaning": ""
    },
    {
        "phonetics": "pāsä T`H`",
        "meaning": "'Passover'",
        "origin_explanation": "from Gk. paskha 'Passover', transcription of Aram. pashā. See also päsikä, fäsikä, fäsh I",
        "ethiopic_word": "",
        "amharic_meaning": ""
    },
    {
        "phonetics": "pesä, pisä T`H` i T`H`",
        "meaning": "'pitch, tar'",
        "origin_explanation": "from Gk. pissa 'pitch'.",
        "ethiopic_word": "",
        "amharic_meaning": ""
    },
    {
        "phonetics": "päsikä I T`H`H` (K), päsakä T`H`H` (T)",
        "meaning": "'Passover, Easter'",
        "origin_explanation": "from Gk. paskha 'Passover', transcription of Aram. pashā. See also päsä.",
        "ethiopic_word": "",
        "amharic_meaning": ""
    },
    {
        "phonetics": "päsikä II T`H`H` (T.M)",
        "meaning": "'sorrow, affliction'",
        "origin_explanation": "is probably Tayyä's interpretation of päsikä I.",
        "ethiopic_word": "",
        "amharic_meaning": ""
    },
    {
        "phonetics": "paskimā, in paskimā həbəst T`H`H`, T`H`H` (Lt)",
        "meaning": "'dry bread'",
        "origin_explanation": "see also pak`simā.",
        "ethiopic_word": "",
        "amharic_meaning": ""
    },
    {
        "phonetics": "pəsaltē T`H`T` (K), pəsaltē T`H`M` (Lt)",
        "meaning": "'psalm'; rather 'psalmist' (in view of the Greek)",
        "origin_explanation": "from Gk. psaltēs 'harper, psalmist, one who sings psalms in the church'. See also 'absalates.",
        "ethiopic_word": "",
        "amharic_meaning": ""
    }
]